[
    {
        "video_id": "IqL-ZunFfpk",
        "title": "Pop The Balloons, Win $10,000",
        "publishedAt": "2026-03-17T16:00:04Z",
        "duration": "PT22S",
        "viewCount": "52139840",
        "likeCount": "918265",
        "commentCount": "8929"
    },
    {
        "video_id": "purAsH7pXTQ",
        "title": "5 Strangers Split $100,000",
        "publishedAt": "2026-03-13T16:00:00Z",
        "duration": "PT1M4S",
        "viewCount": "38293910",
        "likeCount": "1239080",
        "commentCount": "16303"
    },
    {
        "video_id": "IEuDUhGIJ5c",
        "title": "My Chocolate Factory Blew Up",
        "publishedAt": "2026-03-10T16:00:01Z",
        "duration": "PT1M10S",
        "viewCount": "12229241",
        "likeCount": "690367",
        "commentCount": "17304"
    },
    {
        "video_id": "AoN1K4c7VKE",
        "title": "Survive 30 Days Stranded With Your Ex, Win $250,000",
        "publishedAt": "2026-03-07T17:00:02Z",
        "duration": "PT30M4S",
        "viewCount": "97308549",
        "likeCount": "2001225",
        "commentCount": "132043"
    },
    {
        "video_id": "IcuJ3vO_t3k",
        "title": "Would You Steal Money From A Stranger?",
        "publishedAt": "2026-03-06T18:00:01Z",
        "duration": "PT27S",
        "viewCount": "58538352",
        "likeCount": "1589153",
        "commentCount": "9404"
    },
    {
        "video_id": "c9VS_cgInT4",
        "title": "Subscribe, I’ll Double Your Bank Account",
        "publishedAt": "2026-02-28T20:00:03Z",
        "duration": "PT31S",
        "viewCount": "83927122",
        "likeCount": "1523410",
        "commentCount": "17385"
    },
    {
        "video_id": "KaUuPNYHFNg",
        "title": "I Built a School in Mexico",
        "publishedAt": "2026-02-22T17:00:00Z",
        "duration": "PT40S",
        "viewCount": "15642252",
        "likeCount": "650832",
        "commentCount": "12902"
    },
    {
        "video_id": "5OLs1GWB4OA",
        "title": "I Built 10 Schools Around The World",
        "publishedAt": "2026-02-21T17:00:07Z",
        "duration": "PT16M5S",
        "viewCount": "53369637",
        "likeCount": "2148506",
        "commentCount": "90852"
    },
    {
        "video_id": "hjkbqeWQAM8",
        "title": "Every Step You Take, Win $1,000",
        "publishedAt": "2026-02-18T20:00:03Z",
        "duration": "PT42S",
        "viewCount": "81696276",
        "likeCount": "1275634",
        "commentCount": "8270"
    },
    {
        "video_id": "XbaZ45LVzzM",
        "title": "Surprising My Fiancée With A Chocolate Heart",
        "publishedAt": "2026-02-12T17:00:01Z",
        "duration": "PT37S",
        "viewCount": "71166928",
        "likeCount": "1825830",
        "commentCount": "15399"
    },
    {
        "video_id": "gar4U3n-ILY",
        "title": "Guess What Age Punched You",
        "publishedAt": "2026-02-09T17:00:00Z",
        "duration": "PT37S",
        "viewCount": "238952989",
        "likeCount": "3660246",
        "commentCount": "26608"
    },
    {
        "video_id": "9WEQts7b8Pw",
        "title": "Ages 1 - 100 Race For $250,000!",
        "publishedAt": "2026-02-07T17:00:01Z",
        "duration": "PT23M31S",
        "viewCount": "79125456",
        "likeCount": "1500253",
        "commentCount": "79450"
    },
    {
        "video_id": "_sBRk9ADpK8",
        "title": "Flip a Coin, Win $30,000",
        "publishedAt": "2026-01-27T17:00:03Z",
        "duration": "PT47S",
        "viewCount": "710982856",
        "likeCount": "6279732",
        "commentCount": "30886"
    },
    {
        "video_id": "kNLr-cduzuo",
        "title": "Wait... Was He Famous?",
        "publishedAt": "2026-01-25T20:00:01Z",
        "duration": "PT14S",
        "viewCount": "128307950",
        "likeCount": "3084824",
        "commentCount": "28141"
    },
    {
        "video_id": "pAnGwRiQ4-4",
        "title": "$1 vs $1,000,000,000 Futuristic Tech!",
        "publishedAt": "2026-01-24T17:00:01Z",
        "duration": "PT23M4S",
        "viewCount": "117650871",
        "likeCount": "2811366",
        "commentCount": "85439"
    },
    {
        "video_id": "wSh8fAFWEWs",
        "title": "Survivor vs Beast Games",
        "publishedAt": "2026-01-16T19:00:01Z",
        "duration": "PT28S",
        "viewCount": "31079200",
        "likeCount": "793260",
        "commentCount": "13912"
    },
    {
        "video_id": "3GNyw4uaAqU",
        "title": "Subscribe for an iPhone",
        "publishedAt": "2026-01-13T19:00:04Z",
        "duration": "PT15S",
        "viewCount": "1110448608",
        "likeCount": "6211918",
        "commentCount": "164325"
    },
    {
        "video_id": "ywIcdSNJolo",
        "title": "Pass the Phone",
        "publishedAt": "2026-01-09T19:00:05Z",
        "duration": "PT23S",
        "viewCount": "73870460",
        "likeCount": "1723173",
        "commentCount": "12836"
    },
    {
        "video_id": "QJI0an6irrA",
        "title": "30 Celebrities Fight For $1,000,000!",
        "publishedAt": "2026-01-07T20:00:09Z",
        "duration": "PT41M58S",
        "viewCount": "112095745",
        "likeCount": "2507749",
        "commentCount": "116530"
    },
    {
        "video_id": "mktYW177p6U",
        "title": "Guess the Animal",
        "publishedAt": "2026-01-06T17:00:02Z",
        "duration": "PT53S",
        "viewCount": "364743004",
        "likeCount": "5058637",
        "commentCount": "17976"
    },
    {
        "video_id": "7aE4EhHXzlA",
        "title": "I Paid Everyone Stuck in Traffic",
        "publishedAt": "2025-12-26T17:00:05Z",
        "duration": "PT27S",
        "viewCount": "93436262",
        "likeCount": "2635914",
        "commentCount": "39617"
    },
    {
        "video_id": "IJkB-oapuks",
        "title": "Giving Away $1,000,000 in Gifts To My Subscribers",
        "publishedAt": "2025-12-21T17:00:01Z",
        "duration": "PT19S",
        "viewCount": "1037765151",
        "likeCount": "7601903",
        "commentCount": "191727"
    },
    {
        "video_id": "ZFoNBxpXen4",
        "title": "Survive 30 Days Trapped In The Sky, Win $250,000",
        "publishedAt": "2025-12-20T17:00:01Z",
        "duration": "PT37M26S",
        "viewCount": "163480142",
        "likeCount": "2747816",
        "commentCount": "106492"
    },
    {
        "video_id": "RB71Z-vVvCc",
        "title": "Find The Real Celebrity, Win $10,000",
        "publishedAt": "2025-12-19T17:00:02Z",
        "duration": "PT33S",
        "viewCount": "193834126",
        "likeCount": "3895715",
        "commentCount": "14094"
    },
    {
        "video_id": "fO5FwBcCJBY",
        "title": "Would You Date Him for $10,000?",
        "publishedAt": "2025-12-12T17:00:03Z",
        "duration": "PT33S",
        "viewCount": "136428976",
        "likeCount": "3436549",
        "commentCount": "22680"
    },
    {
        "video_id": "U-x6KxH1kB4",
        "title": "How Many People to Pull a Plane?",
        "publishedAt": "2025-12-06T19:55:52Z",
        "duration": "PT27S",
        "viewCount": "42317573",
        "likeCount": "876989",
        "commentCount": "13353"
    },
    {
        "video_id": "8bMh8azh3CY",
        "title": "100 Pilots Fight For A Private Jet",
        "publishedAt": "2025-12-06T17:00:01Z",
        "duration": "PT28M46S",
        "viewCount": "136321570",
        "likeCount": "1868348",
        "commentCount": "72247"
    },
    {
        "video_id": "SE9xF1l3ZwE",
        "title": "Hit The Target, Keep The Prize",
        "publishedAt": "2025-12-05T17:00:03Z",
        "duration": "PT26S",
        "viewCount": "51669528",
        "likeCount": "1152189",
        "commentCount": "10019"
    },
    {
        "video_id": "rF00lQ_upzg",
        "title": "Whatever You Hold Onto, You Keep",
        "publishedAt": "2025-12-02T20:00:01Z",
        "duration": "PT26S",
        "viewCount": "64258080",
        "likeCount": "871323",
        "commentCount": "11366"
    },
    {
        "video_id": "uZY9xr-QAk0",
        "title": "Flip a Coin, I’ll Pay For Your College",
        "publishedAt": "2025-11-28T17:00:01Z",
        "duration": "PT34S",
        "viewCount": "269356083",
        "likeCount": "4484167",
        "commentCount": "21665"
    },
    {
        "video_id": "AWBsoArakNY",
        "title": "Who Has The Fastest Reaction Time?",
        "publishedAt": "2025-11-25T17:00:00Z",
        "duration": "PT31S",
        "viewCount": "77397701",
        "likeCount": "1682270",
        "commentCount": "8337"
    },
    {
        "video_id": "Ah_uuTwGOYU",
        "title": "World's Strongest Man Vs Robot",
        "publishedAt": "2025-11-22T17:00:01Z",
        "duration": "PT18M24S",
        "viewCount": "107336267",
        "likeCount": "1920814",
        "commentCount": "65410"
    },
    {
        "video_id": "HISfrcjiNPM",
        "title": "I Surprised 50 Make-A-Wish Kids With Disneyland",
        "publishedAt": "2025-11-21T19:40:01Z",
        "duration": "PT29S",
        "viewCount": "42003134",
        "likeCount": "989313",
        "commentCount": "12851"
    },
    {
        "video_id": "WROMyJAJmp4",
        "title": "Can I Beat An F1 Driver?",
        "publishedAt": "2025-11-18T17:00:01Z",
        "duration": "PT11S",
        "viewCount": "296729803",
        "likeCount": "2661714",
        "commentCount": "12284"
    },
    {
        "video_id": "tAwzBYE18Us",
        "title": "How I Became MrBeef",
        "publishedAt": "2025-11-16T20:00:02Z",
        "duration": "PT46S",
        "viewCount": "35845564",
        "likeCount": "1317280",
        "commentCount": "17171"
    },
    {
        "video_id": "LyFMbY-c_Lc",
        "title": "I Raced Noah Lyles",
        "publishedAt": "2025-11-14T17:00:01Z",
        "duration": "PT32S",
        "viewCount": "337180643",
        "likeCount": "4170183",
        "commentCount": "10945"
    },
    {
        "video_id": "3RmOvxilbPM",
        "title": "100 People Vs World’s Biggest Trap!",
        "publishedAt": "2025-11-08T17:00:00Z",
        "duration": "PT30M43S",
        "viewCount": "107780090",
        "likeCount": "1912707",
        "commentCount": "83738"
    },
    {
        "video_id": "R7MkZL5i3FQ",
        "title": "Giving Trick-or-Treaters Weirder and Weirder Gifts",
        "publishedAt": "2025-11-07T17:00:05Z",
        "duration": "PT27S",
        "viewCount": "156196099",
        "likeCount": "1714708",
        "commentCount": "12575"
    },
    {
        "video_id": "26QQE7EsnLA",
        "title": "MrBeast Lab Disaster!",
        "publishedAt": "2025-11-03T17:00:01Z",
        "duration": "PT1M7S",
        "viewCount": "34964351",
        "likeCount": "1324023",
        "commentCount": "16487"
    },
    {
        "video_id": "PryTbmudhS8",
        "title": "Can We Stop World's Best Tennis Player",
        "publishedAt": "2025-10-31T16:00:02Z",
        "duration": "PT23S",
        "viewCount": "90104599",
        "likeCount": "1455892",
        "commentCount": "11449"
    },
    {
        "video_id": "Oo9EbArcQ1c",
        "title": "I Saved 1,000 Animals From Dying",
        "publishedAt": "2025-10-25T16:00:01Z",
        "duration": "PT17M36S",
        "viewCount": "171134682",
        "likeCount": "3230565",
        "commentCount": "58730"
    },
    {
        "video_id": "yWEUL3crU_E",
        "title": "I Baked a Cake In a Race Car",
        "publishedAt": "2025-10-21T16:00:01Z",
        "duration": "PT38S",
        "viewCount": "44191842",
        "likeCount": "817881",
        "commentCount": "7820"
    },
    {
        "video_id": "JgJrQnDIRgg",
        "title": "First to Answer the Phone, Wins $10,000",
        "publishedAt": "2025-10-17T16:00:00Z",
        "duration": "PT46S",
        "viewCount": "66783223",
        "likeCount": "2000280",
        "commentCount": "9720"
    },
    {
        "video_id": "gtkqnhN0VkU",
        "title": "Answer The Door, Win $10,000",
        "publishedAt": "2025-10-14T16:00:00Z",
        "duration": "PT31S",
        "viewCount": "85777261",
        "likeCount": "2493426",
        "commentCount": "51891"
    },
    {
        "video_id": "oBXSvS2QKxU",
        "title": "100 Kids Vs World's Strongest Man!",
        "publishedAt": "2025-10-11T16:00:00Z",
        "duration": "PT27M21S",
        "viewCount": "160835782",
        "likeCount": "2788863",
        "commentCount": "51671"
    },
    {
        "video_id": "UTdcX1e0cMA",
        "title": "Jump Over The Lava, Win!",
        "publishedAt": "2025-10-10T16:00:01Z",
        "duration": "PT1M3S",
        "viewCount": "76239833",
        "likeCount": "2064818",
        "commentCount": "11870"
    },
    {
        "video_id": "oiZvK6MY7tI",
        "title": "Call Your Ex, Win $10,000",
        "publishedAt": "2025-10-07T16:00:00Z",
        "duration": "PT34S",
        "viewCount": "110082230",
        "likeCount": "2824728",
        "commentCount": "10354"
    },
    {
        "video_id": "F0OkwXKcPSE",
        "title": "Hi Me In 10 Years",
        "publishedAt": "2025-10-04T16:00:07Z",
        "duration": "PT3M14S",
        "viewCount": "58651025",
        "likeCount": "3621823",
        "commentCount": "112833"
    },
    {
        "video_id": "686PL7rt654",
        "title": "World’s Fastest Dinner Date",
        "publishedAt": "2025-10-03T16:00:03Z",
        "duration": "PT34S",
        "viewCount": "274348059",
        "likeCount": "3726607",
        "commentCount": "12879"
    },
    {
        "video_id": "zo7i8VTpfNM",
        "title": "Would You Risk Dying For $500,000?",
        "publishedAt": "2025-09-27T16:00:04Z",
        "duration": "PT25M26S",
        "viewCount": "122919497",
        "likeCount": "2227408",
        "commentCount": "31436"
    }
]